MANIFEST.in
README.rst
setup.py
ueditor/__init__.py
ueditor/fields.py
ueditor/site.py
ueditor/widgets.py
ueditor.egg-info/PKG-INFO
ueditor.egg-info/SOURCES.txt
ueditor.egg-info/dependency_links.txt
ueditor.egg-info/not-zip-safe
ueditor.egg-info/requires.txt
ueditor.egg-info/top_level.txt
ueditor/static/.DS_Store
ueditor/static/ueditor/.DS_Store
ueditor/static/ueditor/ueditor.all.js
ueditor/static/ueditor/ueditor.all.min.js
ueditor/static/ueditor/ueditor.config.js
ueditor/static/ueditor/ueditor.init.js
ueditor/static/ueditor/ueditor.parse.js
ueditor/static/ueditor/ueditor.parse.min.js
ueditor/static/ueditor/dialogs/internal.js
ueditor/static/ueditor/dialogs/anchor/anchor.html
ueditor/static/ueditor/dialogs/attachment/attachment.css
ueditor/static/ueditor/dialogs/attachment/attachment.html
ueditor/static/ueditor/dialogs/attachment/attachment.js
ueditor/static/ueditor/dialogs/attachment/fileTypeImages/icon_chm.gif
ueditor/static/ueditor/dialogs/attachment/fileTypeImages/icon_default.png
ueditor/static/ueditor/dialogs/attachment/fileTypeImages/icon_doc.gif
ueditor/static/ueditor/dialogs/attachment/fileTypeImages/icon_exe.gif
ueditor/static/ueditor/dialogs/attachment/fileTypeImages/icon_jpg.gif
ueditor/static/ueditor/dialogs/attachment/fileTypeImages/icon_mp3.gif
ueditor/static/ueditor/dialogs/attachment/fileTypeImages/icon_mv.gif
ueditor/static/ueditor/dialogs/attachment/fileTypeImages/icon_pdf.gif
ueditor/static/ueditor/dialogs/attachment/fileTypeImages/icon_ppt.gif
ueditor/static/ueditor/dialogs/attachment/fileTypeImages/icon_psd.gif
ueditor/static/ueditor/dialogs/attachment/fileTypeImages/icon_rar.gif
ueditor/static/ueditor/dialogs/attachment/fileTypeImages/icon_txt.gif
ueditor/static/ueditor/dialogs/attachment/fileTypeImages/icon_xls.gif
ueditor/static/ueditor/dialogs/attachment/images/alignicon.gif
ueditor/static/ueditor/dialogs/attachment/images/alignicon.png
ueditor/static/ueditor/dialogs/attachment/images/bg.png
ueditor/static/ueditor/dialogs/attachment/images/file-icons.gif
ueditor/static/ueditor/dialogs/attachment/images/file-icons.png
ueditor/static/ueditor/dialogs/attachment/images/icons.gif
