Metadata-Version: 1.0
Name: ueditor
Version: 1.2
Summary: django ueditor plugin
Home-page: https://github.com/newpanjing/ueditor.git
Author: panjing
Author-email: newpanjing@icloud.com
License: Apache Listen 2.0
Platform: UNKNOWN
